anchorpy_core-0.2.0.dist-info/METADATA
anchorpy_core-0.2.0.dist-info/WHEEL
anchorpy_core-0.2.0.dist-info/license_files/LICENSE
anchorpy_core/idl.pyi
anchorpy_core/__init__.py
anchorpy_core/py.typed
anchorpy_core/anchorpy_core.abi3.so
anchorpy_core-0.2.0.dist-info/RECORD
