Metadata-Version: 2.1
Name: anchorpy-core
Version: 0.2.0
Classifier: Programming Language :: Rust
Classifier: Programming Language :: Python :: Implementation :: CPython
Requires-Dist: jsonalias ==0.1.1
License-File: LICENSE
Summary: Python bindings for Anchor Rust code
Author-email: kevinheavey <kevinheavey123@gmail.com>
License: Apache-2.0
Requires-Python: >=3.9
Project-URL: homepage, https://github.com/kevinheavey/anchorpy-core
Project-URL: documentation, https://kevinheavey.github.io/anchorpy-core/
Project-URL: repository, https://github.com/kevinheavey/anchorpy-core
Project-URL: changelog, https://github.com/kevinheavey/anchorpy-core/blob/main/CHANGELOG.md
